geojson_transformer/__init__.py
geojson_transformer/config.json
geojson_transformer/transformer.py
utils/__init__.py
utils/geo_utils.py
geojson_transformer-0.0.7.dist-info/LICENSE
geojson_transformer-0.0.7.dist-info/METADATA
geojson_transformer-0.0.7.dist-info/WHEEL
geojson_transformer-0.0.7.dist-info/top_level.txt
geojson_transformer-0.0.7.dist-info/RECORD
