Metadata-Version: 2.1
Name: geojson-transformer
Version: 0.0.7
Summary: Tool for extracting data from geojson or gpx files
Home-page: https://github.com/ivan4oto/gpx_geojson_py/
Author: Ivan Gochev
Author-email: ivan.gotchev94@gmail.comm
License: UNKNOWN
Project-URL: Bug Tracker, https://github.com/ivan4oto/gpx_geojson_py/issues
Platform: UNKNOWN
Classifier: Programming Language :: Python :: 3
Classifier: License :: OSI Approved :: MIT License
Classifier: Operating System :: OS Independent
Requires-Python: >=3.6
License-File: LICENSE
Requires-Dist: lxml
